{"name":"Positive Login test","id":"login;positive-login-test","testSteps":[{"number":1,"description":"Example: {URL\u003dhttps://practicetestautomation.com/practice-test-login/, username\u003dstudent, password\u003dPassword123, expectedUrlPart\u003dpracticetestautomation.com/logged-in-successfully/, expectedText\u003dCongratulations, expectedText2\u003dSuccessfully logged in}","duration":5681,"startTime":"2024-12-24T11:00:33.852+05:30[Asia/Kolkata]","screenshots":[{"screenshot":"25187ee618605f3ec27368535f44a5071265700b0306f54673b6f2cacdb13d6b.png","timeStamp":1735018239533}],"result":"SUCCESS","precondition":false,"level":0,"children":[{"number":2,"description":"Given I opened the app using following https://practicetestautomation.com/practice-test-login/","duration":3605,"startTime":"2024-12-24T11:00:33.855+05:30[Asia/Kolkata]","screenshots":[{"screenshot":"6d9d7bbd5c4ae6b93391511b521720b33dbe7a469d6b65886ed585f2edcf96d6.png","timeStamp":1735018237460}],"result":"SUCCESS","precondition":false,"level":1},{"number":3,"description":"When I enter username student and password Password123","duration":692,"startTime":"2024-12-24T11:00:37.463+05:30[Asia/Kolkata]","screenshots":[{"screenshot":"6d9d7bbd5c4ae6b93391511b521720b33dbe7a469d6b65886ed585f2edcf96d6.png","timeStamp":1735018237463},{"screenshot":"de44c42d7fe2dfa676176e02d6437f89094b887a30f9c5100b85faf6b6ece2ef.png","timeStamp":1735018238154}],"result":"SUCCESS","precondition":false,"level":1},{"number":4,"description":"And I click on the Submit button","duration":1040,"startTime":"2024-12-24T11:00:38.156+05:30[Asia/Kolkata]","screenshots":[{"screenshot":"de44c42d7fe2dfa676176e02d6437f89094b887a30f9c5100b85faf6b6ece2ef.png","timeStamp":1735018238157},{"screenshot":"25187ee618605f3ec27368535f44a5071265700b0306f54673b6f2cacdb13d6b.png","timeStamp":1735018239196}],"result":"SUCCESS","precondition":false,"level":1},{"number":5,"description":"Then I verify new page URL contains practicetestautomation.com/logged-in-successfully/","duration":9,"startTime":"2024-12-24T11:00:39.197+05:30[Asia/Kolkata]","screenshots":[{"screenshot":"25187ee618605f3ec27368535f44a5071265700b0306f54673b6f2cacdb13d6b.png","timeStamp":1735018239197},{"screenshot":"25187ee618605f3ec27368535f44a5071265700b0306f54673b6f2cacdb13d6b.png","timeStamp":1735018239206}],"result":"SUCCESS","precondition":false,"level":1},{"number":6,"description":"And I verify new page contains expected text Congratulations or Successfully logged in","duration":17,"startTime":"2024-12-24T11:00:39.206+05:30[Asia/Kolkata]","screenshots":[{"screenshot":"25187ee618605f3ec27368535f44a5071265700b0306f54673b6f2cacdb13d6b.png","timeStamp":1735018239206},{"screenshot":"25187ee618605f3ec27368535f44a5071265700b0306f54673b6f2cacdb13d6b.png","timeStamp":1735018239223}],"result":"SUCCESS","precondition":false,"level":1},{"number":7,"description":"And I verify logout button is displayed on the new page","duration":308,"startTime":"2024-12-24T11:00:39.223+05:30[Asia/Kolkata]","screenshots":[{"screenshot":"25187ee618605f3ec27368535f44a5071265700b0306f54673b6f2cacdb13d6b.png","timeStamp":1735018239224},{"screenshot":"25187ee618605f3ec27368535f44a5071265700b0306f54673b6f2cacdb13d6b.png","timeStamp":1735018239531}],"result":"SUCCESS","precondition":false,"level":1}]}],"userStory":{"id":"login","storyName":"Login","path":"src/test/resources/login.feature","type":"feature"},"featureTag":{"name":"Resources/Login","type":"feature","displayName":"Resources/Login"},"title":"Positive Login test","startTime":"2024-12-24T11:00:33.816+05:30[Asia/Kolkata]","duration":5787,"projectKey":"","isManualTestingUpToDate":false,"dataTable":{"headers":["URL","username","password","expectedUrlPart","expectedText","expectedText2"],"rows":[{"values":["https://practicetestautomation.com/practice-test-login/","student","Password123","practicetestautomation.com/logged-in-successfully/","Congratulations","Successfully logged in"],"result":"SUCCESS"}],"predefinedRows":true,"scenarioOutline":"Given I opened the app using following \u003cURL\u003e\n\rWhen I enter username \u003cusername\u003e and password \u003cpassword\u003e\n\rAnd I click on the Submit button\n\rThen I verify new page URL contains \u003cexpectedUrlPart\u003e\n\rAnd I verify new page contains expected text \u003cexpectedText\u003e or \u003cexpectedText2\u003e\n\rAnd I verify logout button is displayed on the new page\n\r","dataSetDescriptors":[{"startRow":0,"rowCount":0,"name":""}]},"manual":false,"testSource":"Cucumber","result":"SUCCESS","scenarioOutline":"Given I opened the app using following \u003cURL\u003e\nWhen I enter username \u003cusername\u003e and password \u003cpassword\u003e\nAnd I click on the Submit button\nThen I verify new page URL contains \u003cexpectedUrlPart\u003e\nAnd I verify new page contains expected text \u003cexpectedText\u003e or \u003cexpectedText2\u003e\nAnd I verify logout button is displayed on the new page"}